juham_shelly/__init__.py
juham_shelly/py.typed
juham_shelly/shelly.py
juham_shelly/shelly1g3.py
juham_shelly/shelly_plugin.py
juham_shelly/shellydht22.py
juham_shelly/shellyds18B20.py
juham_shelly/shellymotion.py
juham_shelly/shellyplus1.py
juham_shelly/shellypro3.py
juham_shelly/shellypro3em.py
juham_shelly-0.1.16.dist-info/licenses/LICENSE.rst
juham_shelly-0.1.16.dist-info/METADATA
juham_shelly-0.1.16.dist-info/WHEEL
juham_shelly-0.1.16.dist-info/entry_points.txt
juham_shelly-0.1.16.dist-info/top_level.txt
juham_shelly-0.1.16.dist-info/RECORD
